dagster_mlflow/__init__.py
dagster_mlflow/hooks.py
dagster_mlflow/resources.py
dagster_mlflow/version.py
dagster_mlflow-1.0.5.dist-info/LICENSE
dagster_mlflow-1.0.5.dist-info/METADATA
dagster_mlflow-1.0.5.dist-info/WHEEL
dagster_mlflow-1.0.5.dist-info/top_level.txt
dagster_mlflow-1.0.5.dist-info/RECORD
